codegeass/__init__.py
codegeass/py.typed
codegeass/cli/__init__.py
codegeass/cli/main.py
codegeass/cli/commands/__init__.py
codegeass/cli/commands/approval.py
codegeass/cli/commands/cron.py
codegeass/cli/commands/dashboard.py
codegeass/cli/commands/data.py
codegeass/cli/commands/execution.py
codegeass/cli/commands/logs.py
codegeass/cli/commands/notification.py
codegeass/cli/commands/project.py
codegeass/cli/commands/provider.py
codegeass/cli/commands/scheduler.py
codegeass/cli/commands/setup.py
codegeass/cli/commands/skill.py
codegeass/cli/commands/task.py
codegeass/cli/commands/project/__init__.py
codegeass/cli/commands/project/add_remove.py
codegeass/cli/commands/project/init_control.py
codegeass/cli/commands/project/list_show.py
codegeass/cli/commands/project/platforms.py
codegeass/cli/commands/project/utils.py
codegeass/cli/commands/task/__init__.py
codegeass/cli/commands/task/create.py
codegeass/cli/commands/task/list_show.py
codegeass/cli/commands/task/run_control.py
codegeass/cli/commands/task/tag.py
codegeass/cli/commands/task/update_stats.py
codegeass/core/__init__.py
codegeass/core/entities.py
codegeass/core/exceptions.py
codegeass/core/specifications.py
codegeass/core/value_objects.py
codegeass/core/entities/__init__.py
codegeass/core/entities/project.py
codegeass/core/entities/prompt.py
codegeass/core/entities/skill.py
codegeass/core/entities/task.py
codegeass/core/entities/template.py
codegeass/dashboard/__init__.py
codegeass/dashboard/config.py
codegeass/dashboard/dependencies.py
codegeass/dashboard/main.py
codegeass/dashboard/websocket.py
codegeass/dashboard/models/__init__.py
codegeass/dashboard/models/approval.py
codegeass/dashboard/models/execution.py
codegeass/dashboard/models/notification.py
codegeass/dashboard/models/project.py
codegeass/dashboard/models/provider.py
codegeass/dashboard/models/scheduler.py
codegeass/dashboard/models/skill.py
codegeass/dashboard/models/task.py
codegeass/dashboard/routers/__init__.py
codegeass-0.2.11.dist-info/licenses/LICENSE
codegeass-0.2.11.dist-info/METADATA
codegeass-0.2.11.dist-info/WHEEL
codegeass-0.2.11.dist-info/entry_points.txt
codegeass-0.2.11.dist-info/top_level.txt
codegeass-0.2.11.dist-info/RECORD
