Metadata-Version: 2.4
Name: codegeass
Version: 0.2.11
Summary: Task orchestration for AI coding agents - scheduling, skills, approvals, and monitoring
Author: DonTizi
License: MIT
Project-URL: Homepage, https://github.com/dontizi/codegeass
Project-URL: Documentation, https://dontizi.github.io/codegeass/
Project-URL: Repository, https://github.com/dontizi/codegeass.git
Project-URL: Bug Tracker, https://github.com/dontizi/codegeass/issues
Project-URL: Changelog, https://github.com/dontizi/codegeass/blob/main/CHANGELOG.md
Keywords: ai,agents,claude,codex,automation,scheduling,skills,orchestration
Classifier: Development Status :: 3 - Alpha
Classifier: Environment :: Console
Classifier: Intended Audience :: Developers
Classifier: License :: OSI Approved :: MIT License
Classifier: Operating System :: OS Independent
Classifier: Programming Language :: Python :: 3
Classifier: Programming Language :: Python :: 3.11
Classifier: Programming Language :: Python :: 3.12
Classifier: Topic :: Software Development :: Libraries :: Python Modules
Classifier: Topic :: Utilities
Classifier: Typing :: Typed
Requires-Python: >=3.10
License-File: LICENSE
Requires-Dist: pydantic>=2.0
Requires-Dist: click>=8.0
Requires-Dist: rich>=13.0
Requires-Dist: pyyaml>=6.0
Requires-Dist: jinja2>=3.0
Requires-Dist: croniter>=1.0
Requires-Dist: fastapi>=0.100.0
Requires-Dist: uvicorn>=0.20.0
Requires-Dist: websockets>=11.0
Requires-Dist: python-telegram-bot>=21.0
Requires-Dist: httpx>=0.27.0
Provides-Extra: dev
Requires-Dist: pytest>=7.0; extra == "dev"
Requires-Dist: pytest-cov>=4.0; extra == "dev"
Requires-Dist: pytest-asyncio>=0.23.0; extra == "dev"
Requires-Dist: pytest-mock>=3.12.0; extra == "dev"
Requires-Dist: mypy>=1.0; extra == "dev"
Requires-Dist: ruff>=0.1.0; extra == "dev"
Requires-Dist: types-PyYAML>=6.0; extra == "dev"
Requires-Dist: types-croniter>=1.0; extra == "dev"
Provides-Extra: docs
Requires-Dist: mkdocs>=1.5; extra == "docs"
Requires-Dist: mkdocs-material>=9.5; extra == "docs"
Requires-Dist: mkdocs-click>=0.8; extra == "docs"
Requires-Dist: mike>=2.0; extra == "docs"
Dynamic: license-file
